LICENSE.txt
MANIFEST.in
README.md
setup.cfg
setup.py
requirements/base.txt
requirements/extras/postgres.txt
taskrabbit/__init__.py
taskrabbit/__main__.py
taskrabbit/cli.py
taskrabbit/config.py
taskrabbit/operations.py
taskrabbit/utils.py
taskrabbit.egg-info/PKG-INFO
taskrabbit.egg-info/SOURCES.txt
taskrabbit.egg-info/dependency_links.txt
taskrabbit.egg-info/entry_points.txt
taskrabbit.egg-info/not-zip-safe
taskrabbit.egg-info/requires.txt
taskrabbit.egg-info/top_level.txt
taskrabbit/stores/__init__.py
taskrabbit/stores/base.py
taskrabbit/stores/batch.py
taskrabbit/stores/file.py
taskrabbit/stores/postgres.py
taskrabbit/stores/sqlite.py