Metadata-Version: 2.1
Name: taskrabbit
Version: 0.4.1
Summary: Move Celery tasks in and out of RabbitMQ
Home-page: https://github.com/chrislawlor/taskrabbit
Author: Chris Lawlor
License: MIT
Platform: UNKNOWN
Classifier: Development Status :: 3 - Alpha
Classifier: Environment :: Console
Classifier: Intended Audience :: Developers
Classifier: Intended Audience :: System Administrators
Classifier: License :: OSI Approved :: MIT License
Classifier: Programming Language :: Python :: 3
Classifier: Topic :: System :: Distributed Computing
Classifier: Topic :: Software Development :: Object Brokering
Classifier: Operating System :: OS Independent
Requires-Python: >=3.6
Provides-Extra: postgres
